certbot_dns_nextlayer/__init__.py
certbot_dns_nextlayer/dns_nextlayer.py
tests/__init__.py
tests/certbot_dns_nextlayer_test.py
certbot_dns_nextlayer-1.1.2.dist-info/METADATA
certbot_dns_nextlayer-1.1.2.dist-info/WHEEL
certbot_dns_nextlayer-1.1.2.dist-info/entry_points.txt
certbot_dns_nextlayer-1.1.2.dist-info/top_level.txt
certbot_dns_nextlayer-1.1.2.dist-info/RECORD
