Metadata-Version: 2.1
Name: certbot-dns-nextlayer
Version: 1.1.2
Summary: nextlayer DNS Authenticator plugin for Certbot
Home-page: https://github.com/nextlayergmbh/certbot-dns-nextlayer.git
Author: Alexander Holzapfel
Author-email: alexander.holzapfel@nextlayer.at
License: MIT License
Platform: UNKNOWN
Classifier: Development Status :: 5 - Production/Stable
Classifier: Environment :: Plugins
Classifier: Intended Audience :: System Administrators
Classifier: License :: OSI Approved :: MIT License
Classifier: Operating System :: POSIX :: Linux
Classifier: Programming Language :: Python
Classifier: Programming Language :: Python :: 2
Classifier: Programming Language :: Python :: 2.7
Classifier: Programming Language :: Python :: 3
Classifier: Programming Language :: Python :: 3.5
Classifier: Programming Language :: Python :: 3.6
Classifier: Programming Language :: Python :: 3.7
Classifier: Topic :: Internet :: WWW/HTTP
Classifier: Topic :: Security
Classifier: Topic :: System :: Installation/Setup
Classifier: Topic :: System :: Networking
Classifier: Topic :: System :: Systems Administration
Classifier: Topic :: Utilities
Requires-Python: >=2.7, !=3.0.*, !=3.1.*, !=3.2.*, !=3.3.*
Requires-Dist: acme (>=0.31.0)
Requires-Dist: certbot (>=0.31.0)
Requires-Dist: setuptools
Requires-Dist: zope.interface
Requires-Dist: dns-lexicon
Requires-Dist: tldextract (>=3.1.0)
